foliant/preprocessors/removeexcess.py
foliantcontrib.removeexcess-1.0.0.dist-info/LICENSE
foliantcontrib.removeexcess-1.0.0.dist-info/METADATA
foliantcontrib.removeexcess-1.0.0.dist-info/WHEEL
foliantcontrib.removeexcess-1.0.0.dist-info/top_level.txt
foliantcontrib.removeexcess-1.0.0.dist-info/RECORD
