Metadata-Version: 2.1
Name: foliantcontrib.removeexcess
Version: 1.0.0
Summary: Preprocessor for Foliant to remove excessive Markdown files before build.
Home-page: https://github.com/foliant-docs/foliantcontrib.removeexcess
Author: Artemy Lomov
Author-email: artemy@lomov.ru
License: MIT
Platform: any
Classifier: Development Status :: 5 - Production/Stable
Classifier: Environment :: Console
Classifier: Intended Audience :: Developers
Classifier: License :: OSI Approved :: MIT License
Classifier: Operating System :: OS Independent
Classifier: Programming Language :: Python
Classifier: Topic :: Documentation
Classifier: Topic :: Utilities
Requires-Dist: foliant (>=1.0.8)
